oneNeuron/__init__.py
oneNeuron/perceptron.py
oneneuron_pkg_pk1308-0.0.4.dist-info/LICENSE
oneneuron_pkg_pk1308-0.0.4.dist-info/METADATA
oneneuron_pkg_pk1308-0.0.4.dist-info/WHEEL
oneneuron_pkg_pk1308-0.0.4.dist-info/top_level.txt
oneneuron_pkg_pk1308-0.0.4.dist-info/RECORD
